setup.py
ActionCableZwei.egg-info/PKG-INFO
ActionCableZwei.egg-info/SOURCES.txt
ActionCableZwei.egg-info/dependency_links.txt
ActionCableZwei.egg-info/requires.txt
ActionCableZwei.egg-info/top_level.txt
actioncable/__init__.py
actioncable/connection.py
actioncable/message.py
actioncable/subscription.py