Metadata-Version: 1.0
Name: ActionCableZwei
Version: 0.1.4
Summary: Action Cable Client for Python 3
Home-page: https://github.com/tobiasfeistmantl/python-actioncable-zwei
Author: Tobias Feistmantl
Author-email: tobias@myhome-automations.com
License: MIT
Platform: UNKNOWN
